odoo8_addon_account_tax_analysis-8.0.1.0.0.99.dev41-py3.8-nspkg.pth
odoo_addons/account_tax_analysis/README.rst
odoo_addons/account_tax_analysis/__init__.py
odoo_addons/account_tax_analysis/__openerp__.py
odoo_addons/account_tax_analysis/account_tax_analysis.py
odoo_addons/account_tax_analysis/account_tax_analysis_view.xml
odoo_addons/account_tax_analysis/i18n/ab.po
odoo_addons/account_tax_analysis/i18n/account_tax_analysis.pot
odoo_addons/account_tax_analysis/i18n/am.po
odoo_addons/account_tax_analysis/i18n/ar.po
odoo_addons/account_tax_analysis/i18n/bg.po
odoo_addons/account_tax_analysis/i18n/bs.po
odoo_addons/account_tax_analysis/i18n/ca.po
odoo_addons/account_tax_analysis/i18n/ca_ES.po
odoo_addons/account_tax_analysis/i18n/cs.po
odoo_addons/account_tax_analysis/i18n/da.po
odoo_addons/account_tax_analysis/i18n/de.po
odoo_addons/account_tax_analysis/i18n/el_GR.po
odoo_addons/account_tax_analysis/i18n/en_AU.po
odoo_addons/account_tax_analysis/i18n/en_GB.po
odoo_addons/account_tax_analysis/i18n/es.po
odoo_addons/account_tax_analysis/i18n/es_AR.po
odoo_addons/account_tax_analysis/i18n/es_CL.po
odoo_addons/account_tax_analysis/i18n/es_CO.po
odoo_addons/account_tax_analysis/i18n/es_CR.po
odoo_addons/account_tax_analysis/i18n/es_DO.po
odoo_addons/account_tax_analysis/i18n/es_EC.po
odoo_addons/account_tax_analysis/i18n/es_ES.po
odoo_addons/account_tax_analysis/i18n/es_MX.po
odoo_addons/account_tax_analysis/i18n/es_PE.po
odoo_addons/account_tax_analysis/i18n/es_PY.po
odoo_addons/account_tax_analysis/i18n/es_VE.po
odoo_addons/account_tax_analysis/i18n/et.po
odoo_addons/account_tax_analysis/i18n/eu.po
odoo_addons/account_tax_analysis/i18n/fa.po
odoo_addons/account_tax_analysis/i18n/fi.po
odoo_addons/account_tax_analysis/i18n/fr.po
odoo_addons/account_tax_analysis/i18n/fr_CA.po
odoo_addons/account_tax_analysis/i18n/fr_CH.po
odoo_addons/account_tax_analysis/i18n/fr_FR.po
odoo_addons/account_tax_analysis/i18n/gl.po
odoo_addons/account_tax_analysis/i18n/gl_ES.po
odoo8_addon_account_tax_analysis-8.0.1.0.0.99.dev41.dist-info/METADATA
odoo8_addon_account_tax_analysis-8.0.1.0.0.99.dev41.dist-info/WHEEL
odoo8_addon_account_tax_analysis-8.0.1.0.0.99.dev41.dist-info/namespace_packages.txt
odoo8_addon_account_tax_analysis-8.0.1.0.0.99.dev41.dist-info/top_level.txt
odoo8_addon_account_tax_analysis-8.0.1.0.0.99.dev41.dist-info/RECORD
